pylama_quotes/__init__.py
pylama_quotes/direct.py
pylama_quotes/linter_quotes.py
pylama_quotes-0.1.0.dist-info/LICENSE
pylama_quotes-0.1.0.dist-info/METADATA
pylama_quotes-0.1.0.dist-info/WHEEL
pylama_quotes-0.1.0.dist-info/entry_points.txt
pylama_quotes-0.1.0.dist-info/top_level.txt
pylama_quotes-0.1.0.dist-info/RECORD
