Metadata-Version: 2.1
Name: pylama-quotes
Version: 0.1.0
Summary: Simple quote checker for pylama
Home-page: UNKNOWN
Author: Craig Kelly
Author-email: craig.n.kelly@gmail.com
License: MIT
Keywords: pylama,quotes,static,analysis
Platform: UNKNOWN
Classifier: Development Status :: 4 - Beta
Classifier: Intended Audience :: Developers
Classifier: Programming Language :: Python :: 3
Classifier: License :: OSI Approved :: MIT License
Classifier: Topic :: Software Development :: Quality Assurance
Classifier: Topic :: Utilities
